vkpymusic/__init__.py
vkpymusic/client.py
vkpymusic/models/__init__.py
vkpymusic/models/playlist.py
vkpymusic/models/song.py
vkpymusic/models/userinfo.py
vkpymusic/service.py
vkpymusic/token_receiver.py
vkpymusic/utils/__init__.py
vkpymusic/utils/converter.py
vkpymusic/utils/default_handlers.py
vkpymusic/utils/logger.py
vkpymusic/vk_api/__init__.py
vkpymusic/vk_api/vk_api_exception.py
vkpymusic/vk_api/vk_api_extensions.py
vkpymusic/vk_api/vk_api_params.py
vkpymusic/vk_api/vk_api_request.py
vkpymusic/vk_api/vk_api_request_builder.py
vkpymusic/vk_api/vk_api_response.py
vkpymusic-3.5.1.dist-info/LICENSE
vkpymusic-3.5.1.dist-info/METADATA
vkpymusic-3.5.1.dist-info/WHEEL
vkpymusic-3.5.1.dist-info/RECORD
